[
    {
        "position": 1,
        "column": "orderNumber",
        "field": ".orderNumber",
        "key": true,
        "autoGenerate": false,
        "inputField": ".orderNumber",
        "insertValue": null,
        "updateValue": null,
        "version": false,
        "softDelete": false,
        "dataType": "number",
        "notNull": true,
        "keyEligible": true,
        "versionEligible": true,
        "softDeleteEligible": false
    },
    {
        "position": 2,
        "column": "orderDate",
        "field": ".orderDate",
        "key": false,
        "autoGenerate": false,
        "inputField": null,
        "insertValue": null,
        "updateValue": null,
        "version": false,
        "softDelete": false,
        "dataType": "datetime",
        "notNull": true,
        "keyEligible": false,
        "versionEligible": false,
        "softDeleteEligible": false
    },
    {
        "position": 3,
        "column": "requiredDate",
        "field": ".requiredDate",
        "key": false,
        "autoGenerate": false,
        "inputField": null,
        "insertValue": null,
        "updateValue": null,
        "version": false,
        "softDelete": false,
        "dataType": "datetime",
        "notNull": true,
        "keyEligible": false,
        "versionEligible": false,
        "softDeleteEligible": false
    },
    {
        "position": 4,
        "column": "shippedDate",
        "field": ".shippedDate",
        "key": false,
        "autoGenerate": false,
        "inputField": null,
        "insertValue": null,
        "updateValue": null,
        "version": false,
        "softDelete": false,
        "dataType": "datetime",
        "notNull": false,
        "keyEligible": false,
        "versionEligible": false,
        "softDeleteEligible": false
    },
    {
        "position": 5,
        "column": "status",
        "field": ".status",
        "key": false,
        "autoGenerate": false,
        "inputField": null,
        "insertValue": null,
        "updateValue": null,
        "version": false,
        "softDelete": false,
        "dataType": "string",
        "notNull": true,
        "keyEligible": false,
        "versionEligible": false,
        "softDeleteEligible": true
    },
    {
        "position": 6,
        "column": "comments",
        "field": ".comments",
        "key": false,
        "autoGenerate": false,
        "inputField": null,
        "insertValue": null,
        "updateValue": null,
        "version": false,
        "softDelete": false,
        "dataType": "string",
        "notNull": false,
        "keyEligible": false,
        "versionEligible": false,
        "softDeleteEligible": false
    },
    {
        "position": 7,
        "column": "customerNumber",
        "field": ".customerNumber",
        "key": false,
        "autoGenerate": false,
        "inputField": null,
        "insertValue": null,
        "updateValue": null,
        "version": false,
        "softDelete": false,
        "dataType": "number",
        "notNull": true,
        "keyEligible": false,
        "versionEligible": true,
        "softDeleteEligible": false
    }
]